LICENSE
setup.py
masklmm/MaSkLMM.py
masklmm/__init__.py
masklmm.egg-info/PKG-INFO
masklmm.egg-info/SOURCES.txt
masklmm.egg-info/dependency_links.txt
masklmm.egg-info/requires.txt
masklmm.egg-info/top_level.txt